README.rst
click_lock.py
setup.py
click_lock.egg-info/PKG-INFO
click_lock.egg-info/SOURCES.txt
click_lock.egg-info/dependency_links.txt
click_lock.egg-info/not-zip-safe
click_lock.egg-info/requires.txt
click_lock.egg-info/top_level.txt